streaminglogs/__init__.py
streaminglogs/activitylog.py
streaminglogs/exceptionlog.py
streaminglogs/genericlog.py
streaminglogs/logginghandler.py
streaminglogs/streaminglogsservicecontext.py
streaming_logs-1.0.9.dist-info/LICENSE
streaming_logs-1.0.9.dist-info/METADATA
streaming_logs-1.0.9.dist-info/WHEEL
streaming_logs-1.0.9.dist-info/top_level.txt
streaming_logs-1.0.9.dist-info/RECORD
