Metadata-Version: 2.1
Name: streaming-logs
Version: 1.0.9
Summary: Streaming Logs SDK 4 Python.
Home-page: https://location-world@dev.azure.com/location-world/Research%20and%20Development/_git/streaming-logs.py
Author: Location World
Author-email: info@location-world.com
License: MPL-2.0
Platform: UNKNOWN
Classifier: Programming Language :: Python :: 3
Classifier: Programming Language :: Python :: 3.7
Classifier: Operating System :: OS Independent
Requires-Python: >=3.6
License-File: LICENSE
Requires-Dist: requests
